{
  "id": "e873d31e-5afa-49fb-944f-a1428c6a83e4",
  "title": "【必見】退職代行で即日退職！当日朝から仕事を辞める方法と注意点",
  "content": "<p>【必見】退職代行で即日退職！当日朝から仕事を辞める方法と注意点</p>\n<p>仕事を辞めたい、でも上司や同僚に引き止められるのが怖い。そんな悩みを抱えている方は少なくありません。退職の際に引き止められて心理的に追い詰められてしまうケースは後を絶ちません。実際、転職者の16.6%が退職代行を利用しているという調査結果もあります。このように、退職をスムーズに行う手段として退職代行サービスの利用が増えています。</p>\n<p>そこで今回は、即日退職が可能な退職代行サービス「退職あんしん代行」を中心に、<strong>当日朝から辞められる具体的な方法と注意点</strong>をご紹介します。退職に伴う心理的なストレスから解放され、スムーズに転職活動に移行できるよう、退職のプロがサポートします。業界データや利用者の声を踏まえ、安心して利用できる退職代行の選び方もお伝えしますので、退職を検討されている方はぜひ参考にしてください。</p>\n<details>\n    <summary>目次</summary>\n    <nav class=\"toc\">\n      - [構成](#)\n      - [h2: 即日退職は可能？退職代行サービスの仕組みを解説](#h2-)\n      - [h2: 即日退職の具体的な流れと手順](#h2-)\n      - [h2: 違法じゃない？退職代行利用の法的な側面](#h2-)\n      - [h2: おすすめの退職代行サービスと選び方](#h2-)\n      - [h2: よくある質問に答えます【yahoo!知恵袋調査】](#h2-yahoo)\n    </nav>\n  </details>\n\n<h2>h2: 即日退職は可能？退職代行サービスの仕組みを解説</h2>\n<h3>h3: 退職代行で当日辞められる理由とその仕組み</h3>\n<p>退職代行サービスを利用すれば、<strong>当日朝に依頼をしても即日退職が可能</strong>です。その理由は、退職代行業者が代理人として手続きを行うため、自身が直接退職の意思を伝える必要がないためです。</p>\n<p>具体的な仕組みは以下の通りです。</p>\n<ol>\n<li>利用者から退職の依頼を受ける</li>\n<li>業者が代理人として退職届を提出</li>\n<li>退職手続きを完了する</li>\n</ol>\n<p>特に、上司や同僚から引き止められる心配がない点が大きなメリットです。利用者は直接会社に出向く必要がないため、心理的な負担が軽減されます。</p>\n<h3>h3: 当日退職をおこなう際の注意点とは</h3>\n<p>一方で、当日退職を行う際には以下の点に注意が必要です。</p>\n<ul>\n<li><strong>退職日を事前に伝えておく</strong></li>\n<li>返却物がある場合は準備をしておく</li>\n<li>個人情報の取り扱いに気をつける</li>\n</ul>\n<p>急な退職となるため、会社側の対応が遅れがちになります。そのため、退職日を事前に伝えておくことで、スムーズな退職手続きが可能になります。また、社用車や社員証などの返却物がある場合は、準備しておく必要があります。</p>\n<h2>h2: 即日退職の具体的な流れと手順</h2>\n<h3>h3: 退職代行を使った退職手続きのステップ</h3>\n<p>退職代行を利用した退職の具体的な流れは以下の通りです。</p>\n<ol>\n<li><strong>退職代行業者に依頼する</strong></li>\n<li><strong>退職理由や退職日を伝える</strong></li>\n<li><strong>必要書類を業者に送付する</strong></li>\n<li><strong>業者が会社に退職届を提出</strong></li>\n<li><strong>退職が完了する</strong></li>\n</ol>\n<p>退職代行業者に依頼をすれば、あとは業者が会社との手続きを代行してくれます。利用者は直接会社に出向く必要がありません。</p>\n<h3>h3: 当日朝に依頼する際の準備と流れ</h3>\n<p>当日朝に退職代行を依頼する場合の流れは以下の通りです。</p>\n<ol>\n<li><strong>必要書類を準備する</strong></li>\n<li><strong>退職代行業者に電話で依頼する</strong></li>\n<li><strong>必要書類を送付する</strong></li>\n<li><strong>業者が会社に退職届を提出</strong></li>\n<li><strong>退職が完了する</strong></li>\n</ol>\n<p>必ず事前に<strong>退職に必要な書類を準備</strong>しておく必要があります。書類が揃っていれば、当日朝に電話で依頼を行えば、即日退職が可能になります。</p>\n<h2>h2: 違法じゃない？退職代行利用の法的な側面</h2>\n<h3>h3: 退職代行を利用しても問題ない理由</h3>\n<p>退職代行サービスの利用に違法性はありません。なぜなら、<strong>代理人による退職手続きは労働基準法上認められているため</strong>です。</p>\n<p>法的には、労働者本人による直接の意思表示と代理人による意思表示は同等の効力を持ちます。つまり、退職代行業者が代理人として退職手続きを行っても、法的に問題はないのです。</p>\n<h3>h3: トラブルを防ぐための注意ポイント</h3>\n<p>一方で、個人情報の取り扱いには注意が必要です。退職代行業者には、以下の情報を提供する必要があります。</p>\n<ul>\n<li>氏名・住所・生年月日など本人確認情報</li>\n<li>雇用契約書や源泉徴収票など雇用関係の証明書類</li>\n</ul>\n<p><strong>これらの個人情報が外部に漏洩しないよう、信頼できる業者を選ぶ必要があります。</strong></p>\n<h2>h2: おすすめの退職代行サービスと選び方</h2>\n<h3>h3: 失敗しない業者選びの3つのポイント</h3>\n<p>退職代行業者の選び方として、以下の3点に注目することが重要です。</p>\n<ol>\n<li><strong>料金の明朗性</strong></li>\n<li><strong>サポート体制の充実度</strong></li>\n<li><strong>実績と評判</strong></li>\n</ol>\n<p>料金が明確で追加料金がないこと、24時間365日の対応体制があること、そして豊富な実績と高い評判があることが、安心して利用できる業者の条件となります。</p>\n<h3>h3: 評判が良い業者を選ぶ際の注意点</h3>\n<p>評判が良い業者を選ぶ際は、以下の点に注意が必要です。</p>\n<ul>\n<li>口コミサイトだけでなく複数の情報源で評価を確認する</li>\n<li>料金プランに注目し、追加料金がないかチェックする</li>\n<li>対応時間や連絡手段をしっかり確認する</li>\n</ul>\n<p>一見評判が良さそうに見えても、実際は違う場合があります。そのため、<strong>複数の情報源で評価を確認し、料金やサポート体制をしっかり吟味する必要があります。</strong></p>\n<h2>h2: よくある質問に答えます【yahoo!知恵袋調査】</h2>\n<h3>h3: 即日退職したいときの不安点への回答</h3>\n<p>即日退職を検討される方の主な不安点は以下の通りです。</p>\n<ul>\n<li>引き止められるのが怖い(40.7%)  </li>\n<li>言い出せる環境ではない(32.4%)  </li>\n<li>トラブルが心配(23.7%)</li>\n</ul>\n<p>これらの不安は、**退職代行を利用することで解消できます。**業者が代理人として手続きを行うため、引き止められる心配がありません。また、専門家によるサポートを受けられるため、トラブルのリスクも最小限に抑えられます。</p>\n<h3>h3: 当日辞めた後の連絡や対応はどうする？</h3>\n<p>当日退職後の連絡や対応については、以下の点に気をつける必要があります。</p>\n<ul>\n<li>個人的なSNSでの発信は控えめに</li>\n<li>職場の人間関係によっては、直接の連絡は避ける</li>\n<li>重要な引き継ぎ事項は業者経由で伝える</li>\n</ul>\n<p><strong>会社や上司、同僚への連絡は最小限に留め、業者経由で必要最低限の対応を行うのが無難です。</strong></p>\n<p>一方で、退職代行サービスを利用した場合、代行業者が会社との対応窓口となります。そのため、利用者が直接対応する必要はありません。</p>\n<hr>\n<p>以上が「退職あんしん代行」を中心とした、即日退職に関する解説と注意点のまとめです。退職は大きな人生の節目であり、スムーズに次のステップに進めることが重要です。退職代行サービスを上手に活用することで、心理的なストレスを軽減しながら、安心して転職活動に移行できるはずです。</p>\n",
  "category": "trouble-cases",
  "keywords": [
    ""
  ],
  "createdAt": "2024-11-27T20:22:29.469Z",
  "updatedAt": "2024-11-27T20:22:29.469Z"
}